seldump/__init__.py
seldump/__main__.py
seldump/cli.py
seldump/config.py
seldump/consts.py
seldump/database.py
seldump/dbobjects.py
seldump/dbreader.py
seldump/dummywriter.py
seldump/dumper.py
seldump/dumprule.py
seldump/dumpwriter.py
seldump/exceptions.py
seldump/nodes.py
seldump/query.py
seldump/reader.py
seldump/writer.py
seldump/yaml.py
seldump/schema/config.yaml
pg_seldump-0.3.3.dist-info/COPYING
pg_seldump-0.3.3.dist-info/METADATA
pg_seldump-0.3.3.dist-info/WHEEL
pg_seldump-0.3.3.dist-info/entry_points.txt
pg_seldump-0.3.3.dist-info/top_level.txt
pg_seldump-0.3.3.dist-info/RECORD
