Metadata-Version: 2.1
Name: pg-seldump
Version: 0.3.3
Summary: PostgreSQL selective data dump
Home-page: https://github.com/dvarrazzo/pg_seldump
Author: Daniele Varrazzo
Author-email: daniele.varrazzo@gmail.com
License: BSD
Platform: UNKNOWN
Classifier: Development Status :: 4 - Beta
Classifier: Environment :: Console
Classifier: Intended Audience :: Developers
Classifier: Intended Audience :: Information Technology
Classifier: Intended Audience :: Science/Research
Classifier: Intended Audience :: System Administrators
Classifier: License :: OSI Approved :: BSD License
Classifier: Operating System :: POSIX
Classifier: Programming Language :: Python :: 3
Classifier: Topic :: Database
Classifier: Topic :: Software Development
Classifier: Topic :: Software Development :: Testing
Classifier: Topic :: System :: Archiving :: Backup
Classifier: Topic :: System :: Systems Administration
Classifier: Topic :: Utilities
Requires-Python: >= 3.9
License-File: COPYING
Requires-Dist: PyYAML (>=6)
Requires-Dist: jsonschema (>=4.17)
Requires-Dist: psycopg (>=3.1)
Provides-Extra: dev
Requires-Dist: black ; extra == 'dev'
Requires-Dist: flake8 ; extra == 'dev'
Provides-Extra: test
Requires-Dist: pytest (>=7.2) ; extra == 'test'
